{
	"name": "IndieDreams",
	"title": "IndieDreams",

	"header": {
		"background": "transparent",
		"align": "center",

		"brand": {
			"logo": {
				"src": "images/logos/indiecloud-icon.svg",
				"background": "var(--primary-color)",
				"border": "rounded",
				"padding": 2,
				"width": 25,
				"height": 25
			},

			"logotype": {
				"font": "Futura",
				"font_weight": "bold",

				"names": {
					"indie": {
						"first_letter": "150%",
						"color": "var(--secondary-color)"
					},
					"Dreams": {
						"first_letter": "150%",
						"color": "var(--primary-color)"
					}
				}
			}
		},

		"nav": {
			"Uses": {
				"icon": "fa fa-user-circle",
				"href": "#uses"
			},
			"Features": {
				"icon": "fa fa-lightbulb",
				"href": "#features"
			},
			"Tutorial": {
				"icon": "fa fa-chalkboard",
				"href": "#tutorial",
				"platform": "desktop-only"
			},
			"Tokens": {
				"icon": "fa fa-coins",
				"href": "#tokens",
				"platform": "desktop-only"
			},
			"Installation": {
				"icon": "fa fa-computer",
				"href": "#installation",
				"platform": "desktop-only"
			},
			"IndieCloud": {
				"icon": "fa fa-cloud",
				"href": "http://indiecloud.org"
			}
		},

		"buttons": {
			"Sign In": {
				"icon": "fa fa-sign-in-alt",
				"background": "",
				"font": "",
				"color": ""
			},
			"Sign Up": {
				"icon": "fa fa-pencil-alt",
				"background": "",
				"font": "",
				"color": ""
			}
		}
	},

	"welcome": {
		"template": "welcome.tpl",
		"background_image": "images/backgrounds/background-repeat.jpg",

		"masthead": {
			"height": "100% - 70px",
			"background": "linear-gradient(hsla(250, 25%, 33%, 0) 0%, hsla(250, 25%, 15%, 1.0) 100%)"
		},

		"carousel": {
			"template": "welcome/carousel.tpl",
			"color": "white",
			"background": "linear-gradient(hsla(250, 25%, 33%, 0) 0%, hsla(250, 25%, 15%, 1.0) 100%)"
		},

		"splash": {
			"columns": 1,
			"background": "transparent",

			"brand": {
				"logo": {
					"src": "images/logos/cloud-icon.svg",
					"border": "rounded",
					"size": "large",
					"filter": "drop-shadow(5px 5px 15px rgba(0, 0, 0, 0.25))"
				},

				"logotype": {
					"font": "Futura",
					"font_weight": "bold",
					"platform": "mobile",

					"names": {
						"indie": {
							"first_letter": "150%",
							"color": "white"
						},
						"Dreams": {
							"first_letter": "150%",
							"color": "var(--primary-color)"
						}
					}
				}
			},

			"tagline": {
				"text": "Your Dreams, Your Cloud",
				"font": "Futura",
				"font_size": "200%",
				"font_weight": "bold",
				"text_transform": "uppercase",
				"color": "white",
				"background_color": "var(--primary-color)",
				"border": "rounded"
			},

			"description": {
				"text": "Free, friendly, self-hostable cloud-based AI image generation and sharing.",
				"color": "white"
			}
		},

		"ribbons": [{
			"text": "Open Source",
			"font": "Futura",
			"font_weight": "bold",
			"height": 40,
			"line_height": 40,
			"corner": "bottom right",
			"offset": 60,
			"url": "#downloads"
		}, {
			"text": "Free",
			"font": "Futura",
			"font_weight": "bold",
			"height": 40,
			"line_height": 40,
			"corner": "bottom right",
			"offset": 20,
			"color": "black",
			"background": "white",
			"shadow": "none",
			"url": "#installation"
		}, {
			"text": "&nbsp;",
			"font": "Futura",
			"font_weight": "bold",
			"height": 40,
			"line_height": 40,
			"corner": "bottom right",
			"offset": -20,
			"shadow": "none"
		}],

		"message (disabled)": "message.tpl"
	},

	"page": {
		"background": "null",
		"theme": "",

		"heading1": {
			"font": "Futura"
		},

		"heading2": {
			"font": "Futura"
		},

		"heading3": {
			"font": "Futura"
		},

		"footer": {
			"color": "white",
			"background2": "linear-gradient(to bottom, #131321 0%, var(--primary-color) 100%)",
			"background": "url(images/backgrounds/background-repeat.jpg)",

			"overlay": {
				"background": "linear-gradient(hsla(250, 25%, 33%, 0) 0%, hsla(250, 25%, 15%, 1.0) 100%)"
			},

			"brand": {
				"logo": {
					"src": "images/logos/cloud-icon.svg",
					"height": 150,
					"border": "rounded",
					"filter": "drop-shadow(5px 5px 10px rgba(0,0,0,0.2))"
				},

				"logotype": {
					"font": "Futura",
					"font_weight": "bold",

					"names": {
						"indie": {
							"first_letter": "150%",
							"color": "white"
						},
						"Dreams": {
							"first_letter": "150%",
							"color": "var(--primary-color)"
						}
					}
				}
			},

			"info": {
				"Explore": {
					"icon": "fa fa-search",
					"links": {
						"About": {
							"icon": "fa fa-info-circle",
							"href": "#about"
						},
						"Uses": {
							"icon": "fa fa-user-circle",
							"href": "#uses"
						},
						"Features": {
							"icon": "fa fa-lightbulb",
							"href": "#features"
						},
						"Apps": {
							"icon": "fa fa-rocket",
							"href": "#apps"
						}
					}
				},

				"Policies": {
					"icon": "fa fa-gavel",
					"links": {
						"Privacy": {
							"icon": "fa fa-file-alt",
							"href": "#policies/privacy-policy"
						},
						"User Data": {
							"icon": "fa fa-file-alt",
							"href": "#policies/user-data-policy"
						},
						"Terms of Use": {
							"icon": "fa fa-file-alt",
							"href": "#policies/terms-of-use"
						},
						"Code of Conduct": {
							"icon": "fa fa-file-alt",
							"href": "#policies/code-of-conduct"
						}
					}
				},

				"Help": {
					"icon": "fa fa-question-circle",
					"links": {
						"User Guide": {
							"icon": "fa fa-question-circle",
							"href": "#help"
						},
						"Installation": {
							"icon": "fa fa-computer",
							"href": "#installation"
						},
						"Contact Us": {
							"icon": "fa fa-envelope",
							"href": "#contact"
						},
						"IndieCloud": {
							"icon": "fa fa-cloud",
							"href": "http://indiecloud.org"
						}
					}
				}
			}
		}
	},

	"footer": {
		"background": "var(--primary-color)",
		"color": "white",
		"copyright": {
			"year": "2025",
			"logo": "images/logos/indiecloud-icon.svg",
			"url": "http://indiecloud.org",
			"entity": "IndieCloud.org"
		}
	}
}